odoo8_addon_shopinvader_product_tag-8.0.1.0.0.99.dev1-py3.8-nspkg.pth
odoo_addons/shopinvader_product_tag/README.rst
odoo_addons/shopinvader_product_tag/__init__.py
odoo_addons/shopinvader_product_tag/__openerp__.py
odoo_addons/shopinvader_product_tag/data/ir_export_product.xml
odoo8_addon_shopinvader_product_tag-8.0.1.0.0.99.dev1.dist-info/METADATA
odoo8_addon_shopinvader_product_tag-8.0.1.0.0.99.dev1.dist-info/WHEEL
odoo8_addon_shopinvader_product_tag-8.0.1.0.0.99.dev1.dist-info/namespace_packages.txt
odoo8_addon_shopinvader_product_tag-8.0.1.0.0.99.dev1.dist-info/top_level.txt
odoo8_addon_shopinvader_product_tag-8.0.1.0.0.99.dev1.dist-info/RECORD
